hydroshare_on_jupyter/__init__.py
hydroshare_on_jupyter/__main__.py
hydroshare_on_jupyter/cli.py
hydroshare_on_jupyter/config_setup.py
hydroshare_on_jupyter/fs_event_handler.py
hydroshare_on_jupyter/fs_events.py
hydroshare_on_jupyter/hydroshare_resource_cache.py
hydroshare_on_jupyter/server.py
hydroshare_on_jupyter/session.py
hydroshare_on_jupyter/session_struct.py
hydroshare_on_jupyter/session_struct_interface.py
hydroshare_on_jupyter/session_sync_event_listeners.py
hydroshare_on_jupyter/websocket_handler.py
hydroshare_on_jupyter/handlers/__init__.py
hydroshare_on_jupyter/labextension/package.json
hydroshare_on_jupyter/labextension/static/118.49c86799606541644d64.js
hydroshare_on_jupyter/labextension/static/156.88ee642358d2ea21b2bd.js
hydroshare_on_jupyter/labextension/static/170.42c93f014f64b9c5cae9.js
hydroshare_on_jupyter/labextension/static/194.14a5801852aae22c02cb.js
hydroshare_on_jupyter/labextension/static/209.adeaec1897b8a687eb14.js
hydroshare_on_jupyter/labextension/static/209.adeaec1897b8a687eb14.js.LICENSE.txt
hydroshare_on_jupyter/labextension/static/235.3b9934d2be1377bc12b6.js
hydroshare_on_jupyter/labextension/static/235.3b9934d2be1377bc12b6.js.LICENSE.txt
hydroshare_on_jupyter/labextension/static/245.9838382af15e40c83215.js
hydroshare_on_jupyter/labextension/static/299.44c74996b10a9450303f.js
hydroshare_on_jupyter/labextension/static/299.44c74996b10a9450303f.js.LICENSE.txt
hydroshare_on_jupyter/labextension/static/400.d18113636781c965cc38.js
hydroshare_on_jupyter/labextension/static/410.db7f0ccad30701543397.js
hydroshare_on_jupyter/labextension/static/440.61724a70064218ca9dac.js
hydroshare_on_jupyter/labextension/static/440.61724a70064218ca9dac.js.LICENSE.txt
hydroshare_on_jupyter/labextension/static/448.a57032668cad4bb54eff.js
hydroshare_on_jupyter/labextension/static/448.a57032668cad4bb54eff.js.LICENSE.txt
hydroshare_on_jupyter/labextension/static/507.365a69cdf6336ea6faff.js
hydroshare_on_jupyter-0.1.5.dist-info/METADATA
hydroshare_on_jupyter-0.1.5.dist-info/WHEEL
hydroshare_on_jupyter-0.1.5.dist-info/top_level.txt
hydroshare_on_jupyter-0.1.5.dist-info/RECORD
