Metadata-Version: 2.1
Name: hydroshare-on-jupyter
Version: 0.1.5
Summary: A JupyterLab extension for downloading, uploading, editing, and syncing your HydroShare resources without leaving Jupyter.
Home-page: https://github.com/hydroshare/hydroshare_jupyter_sync
Author: Austin Raney
Author-email: araney@cuahsi.org
Maintainer: Austin Raney
Maintainer-email: araney@cuahsi.org
License: UNKNOWN
Platform: UNKNOWN
Requires-Python: >=3.7
Requires-Dist: hsclient (>=0.2.0)
Requires-Dist: jupyterlab
Requires-Dist: notebook
Requires-Dist: requests
Requires-Dist: pydantic[dotenv]
Requires-Dist: watchdog
Provides-Extra: develop
Requires-Dist: pytest ; extra == 'develop'
Requires-Dist: pytest-tornado ; extra == 'develop'
